CompactionAnalyzer/CompactionFunctions.py
CompactionAnalyzer/GUI_old_use_saenopy_instead.py
CompactionAnalyzer/QExtendedGraphicsView.py
CompactionAnalyzer/QtShortCuts.py
CompactionAnalyzer/StructureTensor.py
CompactionAnalyzer/__init__.py
CompactionAnalyzer/plotting.py
CompactionAnalyzer/utilities.py
CompactionAnalyzer-1.0.7.dist-info/LICENSE
CompactionAnalyzer-1.0.7.dist-info/METADATA
CompactionAnalyzer-1.0.7.dist-info/WHEEL
CompactionAnalyzer-1.0.7.dist-info/top_level.txt
CompactionAnalyzer-1.0.7.dist-info/RECORD
