Metadata-Version: 2.2
Name: CompactionAnalyzer
Version: 1.0.7
Summary: A python package to analyze matrix fiber alignment around cells (proxy for cellular forces)
Home-page: 
Download-URL: 
Author: David Böhringer, Andreas Bauer
Author-email: david.boehringer@fau.de
License: GNU General Public License v3.0
Keywords: structure,contractility,compaction,fibrosis,biophysics
License-File: LICENSE
Requires-Dist: numpy>=1.2.6
Requires-Dist: pandas>=0.23.4
Requires-Dist: matplotlib>=2.2.2
Requires-Dist: roipoly>=0.5.3
Requires-Dist: scikit-image>=0.24.0
Requires-Dist: pyyml
Requires-Dist: tqdm
Requires-Dist: openpyxl
Requires-Dist: natsort
Requires-Dist: matplotlib-scalebar
Dynamic: author
Dynamic: author-email
Dynamic: keywords
Dynamic: license
Dynamic: requires-dist
Dynamic: summary
